rabino/__init__.py
rabino/rabino.py
rabino-2.0.4.dist-info/METADATA
rabino-2.0.4.dist-info/WHEEL
rabino-2.0.4.dist-info/top_level.txt
rabino-2.0.4.dist-info/RECORD
